udger/__init__.py
udger/base.py
udger/downloader.py
udger/parser.py
udger/queries.py
udger/wdetector.py
udger_v4-5.0.2.dist-info/LICENSE
udger_v4-5.0.2.dist-info/METADATA
udger_v4-5.0.2.dist-info/WHEEL
udger_v4-5.0.2.dist-info/top_level.txt
udger_v4-5.0.2.dist-info/zip-safe
udger_v4-5.0.2.dist-info/RECORD
