Metadata-Version: 2.1
Name: udger-v4
Version: 5.0.2
Summary: Fast and reliable User Agent parser and IP classifier for Python
Home-page: https://github.com/udger/udger-python-v4
Author: The Udger Team
Author-email: The Udger Team <info@udger.com>
License: MIT License
Project-URL: Homepage, https://github.com/udger/udger-python-v4
Project-URL: Bug Tracker, https://github.com/udger/udger-python-v4/issues
Keywords: parser,useragent
Platform: any
Classifier: Programming Language :: Python :: 3
Classifier: License :: OSI Approved :: MIT License
Classifier: Operating System :: OS Independent
Requires-Python: >=3.5
License-File: LICENSE
Requires-Dist: pysqlite3 (>=0.4.7)
